setup.py
shellcut/__init__.py
shellcut/main.py
shellcut.egg-info/PKG-INFO
shellcut.egg-info/SOURCES.txt
shellcut.egg-info/dependency_links.txt
shellcut.egg-info/entry_points.txt
shellcut.egg-info/requires.txt
shellcut.egg-info/top_level.txt
shellcut/config/default.yaml