Metadata-Version: 1.1
Name: shellcut
Version: 0.2.1
Summary: Shell shortcuts
Home-page: https://github.com/radomirbosak/shellcut
Author: Radomír Bosák
Author-email: radomir.bosak@gmail.com
License: UNKNOWN
Download-URL: https://github.com/radomirbosak/shellcut/archive/0.2.1.tar.gz
Keywords: shell,shortcuts,regex
Platform: UNKNOWN
